{"generated_at":"2026-07-12T03:57:46+00:00","window_days":7,"poll_minutes":15,"note":"Observed close-out = last-seen minus first-seen plus one poll interval; true duration is within \u00b115 min. 'Momentary' = seen in a single poll (resolved in under ~one interval) \u2014 the public-data cousin of a MAIFI momentary-interruption metric. True brownout/voltage-sag data is utility-internal and only surfaces in PUCO reliability filings.","regions":{"MD-WV":{"resolved":3,"avg_min":27.9,"median_min":31.9,"momentary":0,"momentary_pct":0.0},"OH":{"resolved":25,"avg_min":328.2,"median_min":149.0,"momentary":10,"momentary_pct":40.0},"OH-AES":{"resolved":2,"avg_min":15.0,"median_min":15.0,"momentary":2,"momentary_pct":100.0}}}