{"generated_at":"2026-07-12T18:01:50+00:00","window_days":7,"poll_minutes":15,"note":"Observed close-out = last-seen minus first-seen plus one poll interval; true duration is within \u00b115 min. 'Momentary' = seen in a single poll (resolved in under ~one interval) \u2014 the public-data cousin of a MAIFI momentary-interruption metric. True brownout/voltage-sag data is utility-internal and only surfaces in PUCO reliability filings.","regions":{"MD-WV":{"resolved":4,"avg_min":656.0,"median_min":842.2,"momentary":0,"momentary_pct":0.0},"NJ":{"resolved":4,"avg_min":140.2,"median_min":180.3,"momentary":1,"momentary_pct":25.0},"OH":{"resolved":26,"avg_min":524.9,"median_min":149.0,"momentary":10,"momentary_pct":38.5},"OH-AES":{"resolved":18,"avg_min":144.0,"median_min":15.0,"momentary":10,"momentary_pct":55.6},"PA-NY":{"resolved":6,"avg_min":663.1,"median_min":786.4,"momentary":1,"momentary_pct":16.7}}}