{"generated_at":"2026-07-23T11:57:26+00:00","source":"EIA-930 D vs DF (US public domain)","bas":[{"ba":"ISNE","latest_pct":107.5,"latest_period":"2026-07-23T07","max48_pct":113.3,"peak_period":"2026-07-22T07","hours_ge98":43,"settled_hours":48},{"ba":"PJM","latest_pct":108.5,"latest_period":"2026-07-23T07","max48_pct":112.6,"peak_period":"2026-07-21T08","hours_ge98":48,"settled_hours":48},{"ba":"NYIS","latest_pct":100.4,"latest_period":"2026-07-23T04","max48_pct":102.4,"peak_period":"2026-07-21T09","hours_ge98":36,"settled_hours":48}]}